pptestadrianzapala/__init__.py
pptestadrianzapala/m_mod_pptest.py
pptestadrianzapala-0.0.1.dist-info/LICENCE.txt
pptestadrianzapala-0.0.1.dist-info/METADATA
pptestadrianzapala-0.0.1.dist-info/WHEEL
pptestadrianzapala-0.0.1.dist-info/top_level.txt
pptestadrianzapala-0.0.1.dist-info/RECORD
