Metadata-Version: 2.1
Name: pptestadrianzapala
Version: 0.0.1
Summary: My test package
Author-email: AZ <algobitpl@gmail.com>
License: MIT License
Keywords: pptestadrianzapala,funny functions,name,surname,personal data
Classifier: Framework :: IDLE
Classifier: License :: Free For Educational Use
Requires-Python: >=3.0
License-File: LICENCE.txt
Requires-Dist: numpy ; python_version >= "3.0"
